<annotation>
	<folder>train</folder>
	<filename>33.png</filename>
	<path>/Users/bsmita123/object_detection_demo/data/images/train/33.png</path>
	<source>
		<database>Unknown</database>
	</source>
	<size>
		<width>0</width>
		<height>0</height>
		<depth>3</depth>
	</size>
	<segmented>0</segmented>
	<object>
		<name>playscape</name>
		<pose>Unspecified</pose>
		<truncated>0</truncated>
		<difficult>0</difficult>
		<bndbox>
			<xmin>569</xmin>
			<ymin>320</ymin>
			<xmax>751</xmax>
			<ymax>471</ymax>
		</bndbox>
	</object>
	<object>
		<name>basketball</name>
		<pose>Unspecified</pose>
		<truncated>0</truncated>
		<difficult>0</difficult>
		<bndbox>
			<xmin>929</xmin>
			<ymin>567</ymin>
			<xmax>1141</xmax>
			<ymax>716</ymax>
		</bndbox>
	</object>
</annotation>
